{
    "/build/js/app.js": "/build/js/app.js",
    "/build/css/app.css": "/build/css/app.css",
    "/0.93205c089df683d29f65.hot-update.js": "/0.93205c089df683d29f65.hot-update.js",
    "/0.7b4a6a0c916970544825.hot-update.js": "/0.7b4a6a0c916970544825.hot-update.js",
    "/0.12097981d430d8d8dba9.hot-update.js": "/0.12097981d430d8d8dba9.hot-update.js",
    "/0.befa21340990309aeb8b.hot-update.js": "/0.befa21340990309aeb8b.hot-update.js",
    "/0.93eb77c31db1cdf0cb1e.hot-update.js": "/0.93eb77c31db1cdf0cb1e.hot-update.js",
    "/0.f8076ad83b5ed62ea5ec.hot-update.js": "/0.f8076ad83b5ed62ea5ec.hot-update.js",
    "/0.e55c659100c801c5746e.hot-update.js": "/0.e55c659100c801c5746e.hot-update.js",
    "/0.dceb39ff9f1c251a0fdb.hot-update.js": "/0.dceb39ff9f1c251a0fdb.hot-update.js",
    "/0.280f238d4ce01dde309f.hot-update.js": "/0.280f238d4ce01dde309f.hot-update.js",
    "/0.203b4e415932da390525.hot-update.js": "/0.203b4e415932da390525.hot-update.js",
    "/0.e19658a646f33b326560.hot-update.js": "/0.e19658a646f33b326560.hot-update.js"
}